split_lang/__init__.py
split_lang/config.py
split_lang/model.py
split_lang/detect_lang/__init__.py
split_lang/detect_lang/detector.py
split_lang/split/__init__.py
split_lang/split/splitter.py
split_lang/split/utils.py
tests/__init__.py
tests/split_acc.py
tests/test_config.py
tests/test_split.py
tests/test_split_to_substrings.py
tests/data/__init__.py
tests/data/test_data.py
split_lang-2.1.1.dist-info/LICENSE
split_lang-2.1.1.dist-info/METADATA
split_lang-2.1.1.dist-info/WHEEL
split_lang-2.1.1.dist-info/top_level.txt
split_lang-2.1.1.dist-info/RECORD
