Metadata-Version: 2.1
Name: split-lang
Version: 2.1.1
Summary: A package for splitting text by languages through concatenating over split substrings based on their language
Home-page: https://github.com/DoodleBears/langsplit
Author: DoodleBear
Author-email: yangmufeng233@gmail.com
License: MIT
Platform: UNKNOWN
Classifier: Programming Language :: Python :: 3
Classifier: License :: OSI Approved :: MIT License
Classifier: Operating System :: OS Independent
Requires-Python: >=3.9
License-File: LICENSE
Requires-Dist: fast-langdetect>=1.0
Requires-Dist: pydantic
Requires-Dist: budoux
